[
    {
        "id": 101,
        "title": "Дрель DWD 112 S, 701 Вт DeWalt",
        "code": "00000153683",
        "price": 7316,
        "diameterChuck": 20,
        "producer": "Интерскол",
        "appointment": "Дрель-шуруповерт",
        "image": "//tdp.ru/images/p/547/15a07-c43d-11e5-bed3-00259036a192_230x0_1.jpg",
        "hasBattery": true,
        "isNovel": false,
        "isPromo": true
    },
    {
        "id": 102,
        "title": "Дрель FED50001, 500 Bт, Fixtec",
        "code": "00000147820",
        "price": 4312,
        "diameterChuck": 10,
        "producer": "Makita",
        "appointment": "Шуруповерт",
        "image": "//tdp.ru/images/p/fad/1eb5f-68d2-11e5-b9a9-00259036a192_230x0_1.jpg",
        "hasBattery": false,
        "isNovel": false,
        "isPromo": true
    },
    {
        "id": 103,
        "title": "Дрель безударная 6413, 450 Вт Makita",
        "code": "00000129614",
        "price": 16333,
        "diameterChuck": 60,
        "producer": "Bosch",
        "appointment": "Шуруповерт",
        "image": "//tdp.ru/images/p/b8c/3d875-bb85-11e2-99f1-00259036a114_230x0_1.jpg",
        "hasBattery": false,
        "isNovel": true,
        "isPromo": true
    },
    {
        "id": 104,
        "title": "Дрель Д-10/350 ЭР (Т), 350 Вт Интерскол",
        "code": "00000129623",
        "price": 10795,
        "diameterChuck": 70,
        "producer": "Engy",
        "appointment": "Отвертка",
        "image": "//tdp.ru/images/p/c88/e5540-b880-11e2-99f1-00259036a114_230x0_1.jpg",
        "hasBattery": false,
        "isNovel": true,
        "isPromo": false
    },
    {
        "id": 105,
        "title": "Дрель Д-11/540ЭР (Т), 530 Вт Интерскол  ",
        "code": "00000102377",
        "price": 4215,
        "diameterChuck": 50,
        "producer": "Fixtec",
        "appointment": "Шуруповерт",
        "image": "//tdp.ru/images/p/267/c74a9-cca7-11e1-bbf2-00259036a114_230x0_1.jpg",
        "hasBattery": false,
        "isNovel": true,
        "isPromo": false
    },
    {
        "id": 106,
        "title": "Дрель Д-16/1050 Р2, 1050 Вт Интерскол",
        "code": "00000102378",
        "price": 3143,
        "diameterChuck": 70,
        "producer": "Skil",
        "appointment": "Отвертка",
        "image": "//tdp.ru/images/p/8cf/ddc2b-f0a4-11e0-979b-001f29c68b0a_230x0_1.jpg",
        "hasBattery": true,
        "isNovel": false,
        "isPromo": false
    },
    {
        "id": 107,
        "title": "Дрель пневматическая Калибр ПД-6,3/114Р+, 0,63 Мпа",
        "code": "00000143914",
        "price": 6869,
        "diameterChuck": 90,
        "producer": "Skil",
        "appointment": "Дрель-шуруповерт",
        "image": "//tdp.ru/images/p/732/5e713-fbb2-11e4-afe5-00259036a192_230x0_1.jpg",
        "hasBattery": false,
        "isNovel": false,
        "isPromo": true
    },
    {
        "id": 108,
        "title": "Дрель ударная (образец)",
        "code": "00000153758",
        "price": 4388,
        "diameterChuck": 100,
        "producer": "Fixtec",
        "appointment": "Шуруповерт",
        "image": "//tdp.ru/img/no_photo.png",
        "hasBattery": false,
        "isNovel": false,
        "isPromo": true
    },
    {
        "id": 109,
        "title": "Дрель ударная BT-ID 650 E 650Вт Einhell КПП",
        "code": "00000155037",
        "price": 11840,
        "diameterChuck": 90,
        "producer": "Engy",
        "appointment": "Шуруповерт",
        "image": "//tdp.ru/images/p/458/263e1-e6d9-11e5-bed3-00259036a192_230x0_1.jpg",
        "hasBattery": false,
        "isNovel": false,
        "isPromo": true
    },
    {
        "id": 110,
        "title": "Дрель ударная DWD 024, 650 Вт DeWalt",
        "code": "00000153684",
        "price": 8585,
        "diameterChuck": 50,
        "producer": "Fixtec",
        "appointment": "Шуруповерт",
        "image": "//tdp.ru/images/p/3d7/2bb52-c43d-11e5-bed3-00259036a192_230x0_1.jpg",
        "hasBattery": true,
        "isNovel": false,
        "isPromo": true
    },
    {
        "id": 111,
        "title": "Дрель ударная EID-550, 550 Вт, Engy ",
        "code": "00000144711",
        "price": 10620,
        "diameterChuck": 40,
        "producer": "Skil",
        "appointment": "Отвертка",
        "image": "//tdp.ru/images/p/4ef/54a6a-f3b1-11e4-afe5-00259036a192_230x0_1.jpg",
        "hasBattery": true,
        "isNovel": true,
        "isPromo": false
    },
    {
        "id": 112,
        "title": "Дрель ударная FID90001, 900 Вт, Fixtec",
        "code": "00000147821",
        "price": 5763,
        "diameterChuck": 10,
        "producer": "Интерскол",
        "appointment": "Дрель-шуруповерт",
        "image": "//tdp.ru/images/p/9d6/3cb47-68d3-11e5-b9a9-00259036a192_230x0_1.jpg",
        "hasBattery": true,
        "isNovel": true,
        "isPromo": false
    },
    {
        "id": 113,
        "title": "Дрель ударная GSB 13 RE (БЗП) 600 Вт Bosch",
        "code": "00000102380",
        "price": 6042,
        "diameterChuck": 90,
        "producer": "Интерскол",
        "appointment": "Дрель-шуруповерт",
        "image": "//tdp.ru/images/p/4d6/6911b-8b5f-11e0-928f-001f29c68b0a_230x0_1.jpg",
        "hasBattery": true,
        "isNovel": false,
        "isPromo": true
    },
    {
        "id": 114,
        "title": "Дрель ударная GSB 13 RE (ЗВП) 600 Вт Bosch",
        "code": "00000102381",
        "price": 12672,
        "diameterChuck": 100,
        "producer": "Makita",
        "appointment": "Отвертка",
        "image": "//tdp.ru/images/p/687/58212-8c05-11e0-928f-001f29c68b0a_230x0_1.jpg",
        "hasBattery": false,
        "isNovel": true,
        "isPromo": true
    },
    {
        "id": 115,
        "title": "Дрель ударная GSB 16 RE (БЗП) 750 Вт Bosch",
        "code": "00000102382",
        "price": 14935,
        "diameterChuck": 30,
        "producer": "Bosch",
        "appointment": "Отвертка",
        "image": "//tdp.ru/images/p/4d6/6911c-8b5f-11e0-928f-001f29c68b0a_230x0_1.jpg",
        "hasBattery": true,
        "isNovel": true,
        "isPromo": false
    },
    {
        "id": 116,
        "title": "Дрель ударная GSB 16 RE (ЗВП) 750 Вт Bosch",
        "code": "00000102383",
        "price": 13761,
        "diameterChuck": 70,
        "producer": "Engy",
        "appointment": "Дрель-шуруповерт",
        "image": "//tdp.ru/images/p/687/58213-8c05-11e0-928f-001f29c68b0a_230x0_1.jpg",
        "hasBattery": true,
        "isNovel": true,
        "isPromo": false
    },
    {
        "id": 117,
        "title": "Дрель ударная GSB 1600 RE (БЗП) 701 Вт Bosch",
        "code": "00000102384",
        "price": 14792,
        "diameterChuck": 20,
        "producer": "Engy",
        "appointment": "Отвертка",
        "image": "//tdp.ru/images/p/4d6/6911d-8b5f-11e0-928f-001f29c68b0a_230x0_1.jpg",
        "hasBattery": true,
        "isNovel": true,
        "isPromo": false
    },
    {
        "id": 118,
        "title": "Дрель ударная HP 1620, 650 Вт Makita",
        "code": "00000102385",
        "price": 5609,
        "diameterChuck": 20,
        "producer": "Интерскол",
        "appointment": "Шуруповерт",
        "image": "//tdp.ru/images/p/a05/89039-790b-11df-9b7f-001f29c68b0a_230x0_1.jpg",
        "hasBattery": false,
        "isNovel": false,
        "isPromo": true
    },
    {
        "id": 119,
        "title": "Дрель ударная HP 1621 F, 650 Вт Makita",
        "code": "00000102386",
        "price": 9510,
        "diameterChuck": 90,
        "producer": "Bosch",
        "appointment": "Отвертка",
        "image": "//tdp.ru/images/p/a05/8903a-790b-11df-9b7f-001f29c68b0a_230x0_1.jpg",
        "hasBattery": false,
        "isNovel": false,
        "isPromo": true
    },
    {
        "id": 120,
        "title": "Дрель ударная HP 2030, 710 Вт Makita",
        "code": "00000102387",
        "price": 14404,
        "diameterChuck": 70,
        "producer": "Engy",
        "appointment": "Дрель-шуруповерт",
        "image": "//tdp.ru/images/p/a05/8903b-790b-11df-9b7f-001f29c68b0a_230x0_1.jpg",
        "hasBattery": true,
        "isNovel": true,
        "isPromo": false
    },
    {
        "id": 121,
        "title": "Дрель ударная HP1630KX2, 710 Вт Makita",
        "code": "00000153685",
        "price": 11060,
        "diameterChuck": 30,
        "producer": "Engy",
        "appointment": "Шуруповерт",
        "image": "//tdp.ru/images/p/c5f/fff05-c4bf-11e5-bed3-00259036a192_230x0_1.jpg",
        "hasBattery": false,
        "isNovel": false,
        "isPromo": true
    },
    {
        "id": 122,
        "title": "Дрель ударная TH-ID 720/1 E 720 Вт Einhell",
        "code": "00000153772",
        "price": 3089,
        "diameterChuck": 90,
        "producer": "Engy",
        "appointment": "Шуруповерт",
        "image": "//tdp.ru/images/p/4da/848e2-b862-11e5-bed3-00259036a192_230x0_1.jpg",
        "hasBattery": false,
        "isNovel": false,
        "isPromo": true
    },
    {
        "id": 123,
        "title": "Дрель ударная ДУ-13/650 ЭР 650 Вт Интерскол  ",
        "code": "00000102388",
        "price": 5210,
        "diameterChuck": 40,
        "producer": "Makita",
        "appointment": "Шуруповерт",
        "image": "//tdp.ru/images/p/cfa/2d09a-8823-11df-9b7f-001f29c68b0a_230x0_1.jpg",
        "hasBattery": false,
        "isNovel": false,
        "isPromo": false
    },
    {
        "id": 124,
        "title": "Дрель ударная ДУ-13/750 ЭР (Т), 750 Вт Интерскол",
        "code": "00000102389",
        "price": 11901,
        "diameterChuck": 30,
        "producer": "Skil",
        "appointment": "Отвертка",
        "image": "//tdp.ru/images/p/97b/931a1-ccc0-11e1-bbf2-00259036a114_230x0_1.jpg",
        "hasBattery": true,
        "isNovel": true,
        "isPromo": false
    },
    {
        "id": 125,
        "title": "Дрель ударная ДУ-16/1000 ЭР 1000 Вт Интерскол",
        "code": "00000102390",
        "price": 9683,
        "diameterChuck": 30,
        "producer": "Bosch",
        "appointment": "Отвертка",
        "image": "//tdp.ru/images/p/cfa/2d0a2-8823-11df-9b7f-001f29c68b0a_230x0_1.jpg",
        "hasBattery": true,
        "isNovel": false,
        "isPromo": false
    },
    {
        "id": 126,
        "title": "Дрель ударная ДУ-20700, 700 Вт Энергомаш",
        "code": "00000102391",
        "price": 3329,
        "diameterChuck": 20,
        "producer": "Bosch",
        "appointment": "Отвертка",
        "image": "//tdp.ru/images/p/c6a/d0016-d587-11e1-bbf2-00259036a114_230x0_1.jpg",
        "hasBattery": true,
        "isNovel": false,
        "isPromo": true
    },
    {
        "id": 127,
        "title": "Дрель ударная ДЭ- 580ЕРУ 580 Вт Калибр",
        "code": "00000143719",
        "price": 14951,
        "diameterChuck": 20,
        "producer": "Bosch",
        "appointment": "Шуруповерт",
        "image": "//tdp.ru/images/p/dbd/0ca67-f541-11e4-afe5-00259036a192_230x0_1.jpg",
        "hasBattery": true,
        "isNovel": true,
        "isPromo": true
    },
    {
        "id": 128,
        "title": "Дрель ударная ДЭ-680ЕРУ, 580 Вт, Калибр",
        "code": "00000153659",
        "price": 5534,
        "diameterChuck": 80,
        "producer": "Интерскол",
        "appointment": "Дрель-шуруповерт",
        "image": "//tdp.ru/images/p/d1c/a6a8e-aedf-11e5-bed3-00259036a192_230x0_1.jpg",
        "hasBattery": true,
        "isNovel": true,
        "isPromo": false
    },
    {
        "id": 129,
        "title": "Дрель ударная ЕД 0920К, 950 Вт Elitech",
        "code": "00000147446",
        "price": 15717,
        "diameterChuck": 100,
        "producer": "Интерскол",
        "appointment": "Шуруповерт",
        "image": "//tdp.ru/images/p/601/50d63-5df5-11e5-b9a9-00259036a192_230x0_1.jpg",
        "hasBattery": true,
        "isNovel": false,
        "isPromo": false
    },
    {
        "id": 130,
        "title": "Дрель-миксер EM6167, 850 Вт, М14 Boerte",
        "code": "00000146011",
        "price": 11514,
        "diameterChuck": 60,
        "producer": "Engy",
        "appointment": "Шуруповерт",
        "image": "//tdp.ru/images/p/1d8/d7812-262b-11e5-b9a9-00259036a192_230x0_1.jpg",
        "hasBattery": false,
        "isNovel": true,
        "isPromo": true
    },
    {
        "id": 131,
        "title": "Дрель-миксер EM6202B, 1400 Вт, М14 Boerte",
        "code": "00000146012",
        "price": 2972,
        "diameterChuck": 100,
        "producer": "Skil",
        "appointment": "Отвертка",
        "image": "//tdp.ru/images/p/3dd/86450-262b-11e5-b9a9-00259036a192_230x0_1.jpg",
        "hasBattery": false,
        "isNovel": true,
        "isPromo": false
    },
    {
        "id": 132,
        "title": "Дрель-миксер Rubimix-7, 1200 Вт, М14 Rubi ",
        "code": "00000146010",
        "price": 16073,
        "diameterChuck": 90,
        "producer": "Makita",
        "appointment": "Дрель-шуруповерт",
        "image": "//tdp.ru/images/p/e01/76af6-262a-11e5-b9a9-00259036a192_230x0_1.jpg",
        "hasBattery": true,
        "isNovel": true,
        "isPromo": false
    },
    {
        "id": 133,
        "title": "Дрель-миксер Rubimix-9-BL 1200 Вт М14 Rubi",
        "code": "00000102393",
        "price": 10026,
        "diameterChuck": 70,
        "producer": "Fixtec",
        "appointment": "Шуруповерт",
        "image": "//tdp.ru/images/p/c0e/3317e-98df-11e1-b7cf-00259036a114_230x0_1.jpg",
        "hasBattery": true,
        "isNovel": true,
        "isPromo": false
    },
    {
        "id": 134,
        "title": "Дрель-миксер Rubimix-9-BL Plus 1600 Вт М14 Rubi\t",
        "code": "00000133942",
        "price": 15522,
        "diameterChuck": 30,
        "producer": "Engy",
        "appointment": "Дрель-шуруповерт",
        "image": "//tdp.ru/images/p/357/c8fe9-af4d-11e3-b8d5-00259036a114_230x0_1.png",
        "hasBattery": false,
        "isNovel": false,
        "isPromo": true
    },
    {
        "id": 135,
        "title": "Дрель-миксер КМ-60/1000Э, 1050 Вт, М14 Интерскол",
        "code": "00000129624",
        "price": 12184,
        "diameterChuck": 70,
        "producer": "Makita",
        "appointment": "Шуруповерт",
        "image": "//tdp.ru/images/p/c88/e5541-b880-11e2-99f1-00259036a114_230x0_1.jpg",
        "hasBattery": false,
        "isNovel": false,
        "isPromo": true
    },
    {
        "id": 136,
        "title": "Дрель-миксер МС 1400Э 1400 Вт М14 Elitech",
        "code": "00000153687",
        "price": 8713,
        "diameterChuck": 80,
        "producer": "Bosch",
        "appointment": "Шуруповерт",
        "image": "//tdp.ru/images/p/2f9/a9fe5-c4c2-11e5-bed3-00259036a192_230x0_1.jpg",
        "hasBattery": true,
        "isNovel": true,
        "isPromo": true
    },
    {
        "id": 137,
        "title": "Дрель-шуруповерт аккумуляторная (интегрированный аккум.) PSR 1080 LI 10,8 В, Li-Ion Bosch ",
        "code": "00000153753",
        "price": 14324,
        "diameterChuck": 30,
        "producer": "Skil",
        "appointment": "Отвертка",
        "image": "//tdp.ru/images/p/e57/074e6-bad5-11e5-bed3-00259036a192_230x0_1.jpg",
        "hasBattery": false,
        "isNovel": true,
        "isPromo": false
    },
    {
        "id": 138,
        "title": "Дрель-шуруповерт аккумуляторная (образец)",
        "code": "00000153757",
        "price": 3342,
        "diameterChuck": 20,
        "producer": "Fixtec",
        "appointment": "Отвертка",
        "image": "//tdp.ru/img/no_photo.png",
        "hasBattery": true,
        "isNovel": true,
        "isPromo": true
    },
    {
        "id": 139,
        "title": "Дрель-шуруповёрт аккумуляторная 1001LT 12-2, 12 В, 1,2 Ач NiCd, Skil ",
        "code": "00000139827",
        "price": 15643,
        "diameterChuck": 10,
        "producer": "Engy",
        "appointment": "Шуруповерт",
        "image": "//tdp.ru/images/p/e2f/1283e-c0a5-11e4-afe5-00259036a192_230x0_1.jpg",
        "hasBattery": true,
        "isNovel": true,
        "isPromo": true
    },
    {
        "id": 140,
        "title": "Дрель-шуруповерт аккумуляторная 6261 DWPE, 9,6 В, 1,3 Ач NiCd, Makita",
        "code": "00000102394",
        "price": 8917,
        "diameterChuck": 40,
        "producer": "Bosch",
        "appointment": "Дрель-шуруповерт",
        "image": "//tdp.ru/images/p/a05/8903c-790b-11df-9b7f-001f29c68b0a_230x0_1.jpg",
        "hasBattery": false,
        "isNovel": true,
        "isPromo": true
    },
    {
        "id": 141,
        "title": "Дрель-шуруповерт аккумуляторная 6271 DWPE, 12 В, 1,3 Ач NiCd, Makita",
        "code": "00000102395",
        "price": 13018,
        "diameterChuck": 30,
        "producer": "Engy",
        "appointment": "Шуруповерт",
        "image": "//tdp.ru/images/p/a05/8903d-790b-11df-9b7f-001f29c68b0a_230x0_1.jpg",
        "hasBattery": true,
        "isNovel": false,
        "isPromo": false
    },
    {
        "id": 142,
        "title": "Дрель-шуруповерт аккумуляторная 6271 DWPE3, 12 В, 1,3 Ач NiCd, (3 аккумулятора) Makita",
        "code": "00000149092",
        "price": 12946,
        "diameterChuck": 90,
        "producer": "Интерскол",
        "appointment": "Шуруповерт",
        "image": "//tdp.ru/images/p/74f/680af-87be-11e5-9d89-00259036a192_230x0_1.jpg",
        "hasBattery": false,
        "isNovel": false,
        "isPromo": true
    },
    {
        "id": 143,
        "title": "Дрель-шуруповерт аккумуляторная 6281 DWPE, 14,4 В, 1,3 Ач NiCd, Makita",
        "code": "00000134782",
        "price": 6763,
        "diameterChuck": 50,
        "producer": "Skil",
        "appointment": "Отвертка",
        "image": "//tdp.ru/images/p/d4d/442d8-ba6a-11e3-b8d5-00259036a114_230x0_1.jpg",
        "hasBattery": false,
        "isNovel": false,
        "isPromo": false
    },
    {
        "id": 144,
        "title": "Дрель-шуруповерт аккумуляторная 6281DWAE, 14,4 В, 2,0 Ач NiCd, Makita",
        "code": "00000153688",
        "price": 13111,
        "diameterChuck": 40,
        "producer": "Skil",
        "appointment": "Шуруповерт",
        "image": "//tdp.ru/images/p/b92/5a199-c43a-11e5-bed3-00259036a192_230x0_1.jpg",
        "hasBattery": false,
        "isNovel": false,
        "isPromo": false
    },
    {
        "id": 145,
        "title": "Дрель-шуруповерт аккумуляторная 8280 DWPLE, 14,4 В 1,3 Ач Ni-Cd, фонарь, Makita",
        "code": "00000127594",
        "price": 9741,
        "diameterChuck": 30,
        "producer": "Fixtec",
        "appointment": "Шуруповерт",
        "image": "//tdp.ru/images/p/764/3f57d-6cff-11e2-9939-00259036a114_230x0_1.jpg",
        "hasBattery": true,
        "isNovel": false,
        "isPromo": false
    },
    {
        "id": 146,
        "title": "Дрель-шуруповерт аккумуляторная 8281DWAE, 14,4 В, 2,0 Ач NiCd, Makita",
        "code": "00000153689",
        "price": 13249,
        "diameterChuck": 100,
        "producer": "Engy",
        "appointment": "Отвертка",
        "image": "//tdp.ru/images/p/e4d/cfcf9-c43a-11e5-bed3-00259036a192_230x0_1.jpg",
        "hasBattery": false,
        "isNovel": false,
        "isPromo": false
    },
    {
        "id": 147,
        "title": "Дрель-шуруповерт аккумуляторная BHP 453 RFE, 18 В 3,0 Ач Li-Ion , Makita",
        "code": "00000127595",
        "price": 3361,
        "diameterChuck": 10,
        "producer": "Интерскол",
        "appointment": "Отвертка",
        "image": "//tdp.ru/images/p/764/3f57e-6cff-11e2-9939-00259036a114_230x0_1.jpg",
        "hasBattery": true,
        "isNovel": false,
        "isPromo": true
    },
    {
        "id": 148,
        "title": "Дрель-шуруповерт аккумуляторная BS 12C2 LI-152B, 12 В, 1,5 Ач ProLi-Ion, AEG",
        "code": "00000153690",
        "price": 2651,
        "diameterChuck": 50,
        "producer": "Интерскол",
        "appointment": "Дрель-шуруповерт",
        "image": "//tdp.ru/images/p/619/8f03d-c43b-11e5-bed3-00259036a192_230x0_1.jpg",
        "hasBattery": false,
        "isNovel": false,
        "isPromo": false
    },
    {
        "id": 149,
        "title": "Дрель-шуруповерт аккумуляторная BS 12C2 Li-302B, 12 В, 3,0 Ач Li-Ion, AEG",
        "code": "00000153691",
        "price": 14542,
        "diameterChuck": 70,
        "producer": "Engy",
        "appointment": "Отвертка",
        "image": "//tdp.ru/images/p/70a/dc071-c43b-11e5-bed3-00259036a192_230x0_1.jpg",
        "hasBattery": false,
        "isNovel": true,
        "isPromo": true
    },
    {
        "id": 150,
        "title": "Дрель-шуруповерт аккумуляторная BS 12G2 LI-152C, 12 В, 1,5 Ач Li-Ion, AEG",
        "code": "00000153692",
        "price": 15990,
        "diameterChuck": 20,
        "producer": "Makita",
        "appointment": "Отвертка",
        "image": "//tdp.ru/images/p/7a1/1d587-c43b-11e5-bed3-00259036a192_230x0_1.jpg",
        "hasBattery": true,
        "isNovel": true,
        "isPromo": false
    },
    {
        "id": 151,
        "title": "Дрель-шуруповерт аккумуляторная DCD 710 C2, 10,8 В, 1,3 Ач Li-Ion, Compact DeWalt",
        "code": "00000153693",
        "price": 8712,
        "diameterChuck": 60,
        "producer": "Fixtec",
        "appointment": "Отвертка",
        "image": "//tdp.ru/images/p/971/efd28-c43c-11e5-bed3-00259036a192_230x0_1.jpg",
        "hasBattery": true,
        "isNovel": false,
        "isPromo": true
    },
    {
        "id": 152,
        "title": "Дрель-шуруповерт аккумуляторная DCD 734 C2, 14,4 В, 1,3 Ач Li-Ion, Compact DeWalt",
        "code": "00000153694",
        "price": 13384,
        "diameterChuck": 70,
        "producer": "Bosch",
        "appointment": "Шуруповерт",
        "image": "//tdp.ru/images/p/acb/623bb-c43c-11e5-bed3-00259036a192_230x0_1.jpg",
        "hasBattery": false,
        "isNovel": false,
        "isPromo": true
    },
    {
        "id": 153,
        "title": "Дрель-шуруповерт аккумуляторная DCD 771 C2, 18 В, 1,3 Ач Li-Ion, Compact DeWalt",
        "code": "00000153695",
        "price": 16055,
        "diameterChuck": 20,
        "producer": "Skil",
        "appointment": "Шуруповерт",
        "image": "//tdp.ru/images/p/bcf/236d7-c43c-11e5-bed3-00259036a192_230x0_1.jpg",
        "hasBattery": false,
        "isNovel": true,
        "isPromo": true
    },
    {
        "id": 154,
        "title": "Дрель-шуруповерт аккумуляторная DDF343SHE, 14,4 В 1,3 Ач Li-Ion, Makita",
        "code": "00000136281",
        "price": 15541,
        "diameterChuck": 50,
        "producer": "Engy",
        "appointment": "Отвертка",
        "image": "//tdp.ru/images/p/fc1/1c572-05af-11e4-a786-002590c8c920_230x0_1.jpg",
        "hasBattery": false,
        "isNovel": false,
        "isPromo": true
    },
    {
        "id": 155,
        "title": "Дрель-шуруповерт аккумуляторная DDF453RFE, 18 В, 3,0 Ач Li-Ion, Makita",
        "code": "00000153696",
        "price": 2740,
        "diameterChuck": 80,
        "producer": "Bosch",
        "appointment": "Дрель-шуруповерт",
        "image": "//tdp.ru/images/p/e22/141ce-c43c-11e5-bed3-00259036a192_230x0_1.jpg",
        "hasBattery": true,
        "isNovel": false,
        "isPromo": false
    },
    {
        "id": 156,
        "title": "Дрель-шуруповерт аккумуляторная DF 330 DWLE, 10,8 В 1,3 Ач Li-Ion, фонарь, Makita",
        "code": "00000127593",
        "price": 15934,
        "diameterChuck": 70,
        "producer": "Engy",
        "appointment": "Отвертка",
        "image": "//tdp.ru/images/p/764/3f57c-6cff-11e2-9939-00259036a114_230x0_1.jpg",
        "hasBattery": false,
        "isNovel": false,
        "isPromo": false
    },
    {
        "id": 157,
        "title": "Дрель-шуруповерт аккумуляторная DHP453RFE, 18 В 3 Ач Li-Ion, Makita",
        "code": "00000136807",
        "price": 14163,
        "diameterChuck": 40,
        "producer": "Makita",
        "appointment": "Отвертка",
        "image": "//tdp.ru/images/p/072/6ed34-1f06-11e4-94b6-002590c8c920_230x0_1.jpg",
        "hasBattery": true,
        "isNovel": true,
        "isPromo": true
    },
    {
        "id": 158,
        "title": "Дрель-шуруповерт аккумуляторная DW 907 K2 , 12 В, 1,5 Ач NiCd, DeWalt",
        "code": "00000153697",
        "price": 5284,
        "diameterChuck": 60,
        "producer": "Makita",
        "appointment": "Отвертка",
        "image": "//tdp.ru/images/p/2a9/c217a-c43d-11e5-bed3-00259036a192_230x0_1.jpg",
        "hasBattery": true,
        "isNovel": true,
        "isPromo": true
    },
    {
        "id": 159,
        "title": "Дрель-шуруповерт аккумуляторная ECD-121 Pro, 12 В, 1,0 Ач NiCd, Engy ",
        "code": "00000144710",
        "price": 4236,
        "diameterChuck": 80,
        "producer": "Bosch",
        "appointment": "Шуруповерт",
        "image": "//tdp.ru/images/p/5c1/59964-f3b0-11e4-afe5-00259036a192_230x0_1.jpg",
        "hasBattery": true,
        "isNovel": true,
        "isPromo": true
    },
    {
        "id": 160,
        "title": "Дрель-шуруповерт аккумуляторная FCD01201, 12B 1,3 Ач Ni-Cd, Fixtec",
        "code": "00000147817",
        "price": 13817,
        "diameterChuck": 20,
        "producer": "Engy",
        "appointment": "Шуруповерт",
        "image": "//tdp.ru/images/p/737/c868d-68d1-11e5-b9a9-00259036a192_230x0_1.jpg",
        "hasBattery": true,
        "isNovel": false,
        "isPromo": false
    },
    {
        "id": 161,
        "title": "Дрель-шуруповерт аккумуляторная FCD01801, 18B 1,3 Ач Ni-Cd, Fixtec",
        "code": "00000147818",
        "price": 7272,
        "diameterChuck": 10,
        "producer": "Bosch",
        "appointment": "Дрель-шуруповерт",
        "image": "//tdp.ru/images/p/6d9/10f93-6b4f-11e5-9d89-00259036a192_230x0_1.jpg",
        "hasBattery": true,
        "isNovel": false,
        "isPromo": true
    },
    {
        "id": 162,
        "title": "Дрель-шуруповерт аккумуляторная FCD12L01, 12B 1,3 Aч Li-Ion, Fixtec",
        "code": "00000147816",
        "price": 4258,
        "diameterChuck": 60,
        "producer": "Makita",
        "appointment": "Шуруповерт",
        "image": "//tdp.ru/images/p/ad2/f008b-68d0-11e5-b9a9-00259036a192_230x0_1.jpg",
        "hasBattery": true,
        "isNovel": true,
        "isPromo": false
    },
    {
        "id": 163,
        "title": "Дрель-шуруповерт аккумуляторная GSR 12-2,  12 В, 1,5 Ач NiCd Bosch",
        "code": "00000102400",
        "price": 4438,
        "diameterChuck": 50,
        "producer": "Fixtec",
        "appointment": "Отвертка",
        "image": "//tdp.ru/images/p/9e3/af945-8b93-11e0-928f-001f29c68b0a_230x0_1.jpg",
        "hasBattery": true,
        "isNovel": false,
        "isPromo": false
    },
    {
        "id": 164,
        "title": "Дрель-шуруповерт аккумуляторная GSR 14,4-2,  14,4 В, 1,5 Ач NiCd Bosch",
        "code": "00000102402",
        "price": 7586,
        "diameterChuck": 20,
        "producer": "Интерскол",
        "appointment": "Отвертка",
        "image": "//tdp.ru/images/p/9e3/af947-8b93-11e0-928f-001f29c68b0a_230x0_1.jpg",
        "hasBattery": false,
        "isNovel": true,
        "isPromo": true
    },
    {
        "id": 165,
        "title": "Дрель-шуруповерт аккумуляторная GSR 1440-LI 14,4 В, Li-Ion Bosch",
        "code": "00000102403",
        "price": 10972,
        "diameterChuck": 20,
        "producer": "Engy",
        "appointment": "Отвертка",
        "image": "//tdp.ru/images/p/897/54762-7cac-11e1-aa03-00259036a114_230x0_1.jpg",
        "hasBattery": true,
        "isNovel": true,
        "isPromo": true
    },
    {
        "id": 166,
        "title": "Дрель-шуруповерт аккумуляторная GSR 18-2-LI 18 В, 1,5 Ач Li-Ion Bosch",
        "code": "00000136369",
        "price": 11116,
        "diameterChuck": 40,
        "producer": "Интерскол",
        "appointment": "Дрель-шуруповерт",
        "image": "//tdp.ru/images/p/c59/b8bf7-08b8-11e4-94b6-002590c8c920_230x0_1.jpg",
        "hasBattery": true,
        "isNovel": true,
        "isPromo": true
    },
    {
        "id": 167,
        "title": "Дрель-шуруповерт аккумуляторная GSR 18-2-LI Plus 18 В, 1,5 Ач Li-Ion Bosch",
        "code": "00000154768",
        "price": 14450,
        "diameterChuck": 90,
        "producer": "Bosch",
        "appointment": "Дрель-шуруповерт",
        "image": "//tdp.ru/images/p/68c/ea767-dadf-11e5-bed3-00259036a192_230x0_1.png",
        "hasBattery": false,
        "isNovel": false,
        "isPromo": true
    },
    {
        "id": 168,
        "title": "Дрель-шуруповерт аккумуляторная GSR 1800-LI 18 В, 1,5 Ач Li-Ion Bosch",
        "code": "00000102397",
        "price": 10221,
        "diameterChuck": 100,
        "producer": "Bosch",
        "appointment": "Шуруповерт",
        "image": "//tdp.ru/images/p/897/54761-7cac-11e1-aa03-00259036a114_230x0_1.jpg",
        "hasBattery": false,
        "isNovel": true,
        "isPromo": true
    },
    {
        "id": 169,
        "title": "Дрель-шуруповерт аккумуляторная IXO IV Upgrade basic  3,6 В, 1,5 Ач Li-Ion Bosch",
        "code": "00000109618",
        "price": 9599,
        "diameterChuck": 80,
        "producer": "Skil",
        "appointment": "Шуруповерт",
        "image": "//tdp.ru/images/p/897/54760-7cac-11e1-aa03-00259036a114_230x0_1.jpg",
        "hasBattery": false,
        "isNovel": false,
        "isPromo": false
    },
    {
        "id": 170,
        "title": "Дрель-шуруповерт аккумуляторная IXO V  basic 3,6 В, 1,5 Ач Li-Ion Bosch",
        "code": "00000154769",
        "price": 4410,
        "diameterChuck": 80,
        "producer": "Engy",
        "appointment": "Шуруповерт",
        "image": "//tdp.ru/images/p/de5/8e1b0-dadf-11e5-bed3-00259036a192_230x0_1.png",
        "hasBattery": false,
        "isNovel": false,
        "isPromo": true
    },
    {
        "id": 171,
        "title": "Дрель-шуруповерт аккумуляторная TH-CD 14,4 2В, 14,4 В, 1,2 Ач NiCd, Einhell",
        "code": "00000153771",
        "price": 7903,
        "diameterChuck": 10,
        "producer": "Fixtec",
        "appointment": "Дрель-шуруповерт",
        "image": "//tdp.ru/images/p/d2b/704a2-b861-11e5-bed3-00259036a192_230x0_1.jpg",
        "hasBattery": false,
        "isNovel": false,
        "isPromo": false
    },
    {
        "id": 172,
        "title": "Дрель-шуруповерт аккумуляторная ДА - 10,8/2+, 14 В, 1,3 Ач Li-Ion, Калибр",
        "code": "00000153656",
        "price": 6267,
        "diameterChuck": 10,
        "producer": "Engy",
        "appointment": "Дрель-шуруповерт",
        "image": "//tdp.ru/images/p/1d9/9346e-aedf-11e5-bed3-00259036a192_230x0_1.jpg",
        "hasBattery": false,
        "isNovel": true,
        "isPromo": true
    },
    {
        "id": 173,
        "title": "Дрель-шуруповерт аккумуляторная ДА - 12/2+, 12 В, 1,3 Ач Li-Ion, Калибр",
        "code": "00000153657",
        "price": 7306,
        "diameterChuck": 50,
        "producer": "Engy",
        "appointment": "Отвертка",
        "image": "//tdp.ru/images/p/4ff/ed0ef-aedf-11e5-bed3-00259036a192_230x0_1.jpg",
        "hasBattery": false,
        "isNovel": false,
        "isPromo": true
    },
    {
        "id": 174,
        "title": "Дрель-шуруповерт аккумуляторная ДА 10.8ЛK2, 10,8 В, 1,5 Ач Li-Ion, Elitech",
        "code": "00000153698",
        "price": 6023,
        "diameterChuck": 40,
        "producer": "Engy",
        "appointment": "Дрель-шуруповерт",
        "image": "//tdp.ru/images/p/dc3/51384-c4c1-11e5-bed3-00259036a192_230x0_1.jpg",
        "hasBattery": true,
        "isNovel": false,
        "isPromo": true
    },
    {
        "id": 175,
        "title": "Дрель-шуруповерт аккумуляторная ДА 14ЛK2, 14 В, 1,5 Ач Li-Ion, Elitech",
        "code": "00000153700",
        "price": 12488,
        "diameterChuck": 100,
        "producer": "Интерскол",
        "appointment": "Шуруповерт",
        "image": "//tdp.ru/images/p/936/926a4-c4c1-11e5-bed3-00259036a192_230x0_1.jpg",
        "hasBattery": false,
        "isNovel": false,
        "isPromo": false
    },
    {
        "id": 176,
        "title": "Дрель-шуруповерт аккумуляторная ДА 14ЛK2, 14 В, 3,0 Ач Li-Ion, Elitech",
        "code": "00000153701",
        "price": 6405,
        "diameterChuck": 70,
        "producer": "Fixtec",
        "appointment": "Отвертка",
        "image": "//tdp.ru/images/p/a8b/694c4-c4c1-11e5-bed3-00259036a192_230x0_1.jpg",
        "hasBattery": true,
        "isNovel": false,
        "isPromo": false
    },
    {
        "id": 177,
        "title": "Дрель-шуруповерт аккумуляторная ДА 18ЛK2, 14 В, 3,0 Ач Li-Ion, Elitech",
        "code": "00000153702",
        "price": 7097,
        "diameterChuck": 20,
        "producer": "Fixtec",
        "appointment": "Шуруповерт",
        "image": "//tdp.ru/images/p/bec/4d244-c4c1-11e5-bed3-00259036a192_230x0_1.jpg",
        "hasBattery": false,
        "isNovel": true,
        "isPromo": true
    },
    {
        "id": 178,
        "title": "Дрель-шуруповерт аккумуляторная ДА-10/10.8 ЭР, 10,8 В 1,3 Ач Li-Ion, Интерскол",
        "code": "00000134899",
        "price": 12228,
        "diameterChuck": 100,
        "producer": "Bosch",
        "appointment": "Отвертка",
        "image": "//tdp.ru/images/p/6c1/990bb-be31-11e3-b8d5-00259036a114_230x0_1.jpg",
        "hasBattery": true,
        "isNovel": true,
        "isPromo": false
    },
    {
        "id": 179,
        "title": "Дрель-шуруповерт аккумуляторная ДА-10/12 М2 (Т), 12 В, 1,5 Ач NiCd Интерскол",
        "code": "00000146022",
        "price": 11001,
        "diameterChuck": 90,
        "producer": "Skil",
        "appointment": "Шуруповерт",
        "image": "//tdp.ru/images/p/407/ded2c-2632-11e5-b9a9-00259036a192_230x0_1.jpg",
        "hasBattery": true,
        "isNovel": true,
        "isPromo": false
    },
    {
        "id": 180,
        "title": "Дрель-шуруповерт аккумуляторная ДА-10/14,4 М2 (Т), 14,4 В, 1,5 Ач NiCd Интерскол",
        "code": "00000146023",
        "price": 3924,
        "diameterChuck": 10,
        "producer": "Bosch",
        "appointment": "Отвертка",
        "image": "//tdp.ru/images/p/311/ec29e-2633-11e5-b9a9-00259036a192_230x0_1.jpg",
        "hasBattery": false,
        "isNovel": true,
        "isPromo": false
    },
    {
        "id": 181,
        "title": "Дрель-шуруповерт аккумуляторная ДА-12/ЭР-01, 12 В, 1,5 Ач NiCd Интерскол",
        "code": "00000102404",
        "price": 9720,
        "diameterChuck": 60,
        "producer": "Bosch",
        "appointment": "Дрель-шуруповерт",
        "image": "//tdp.ru/images/p/cfa/2d09c-8823-11df-9b7f-001f29c68b0a_230x0_1.jpg",
        "hasBattery": true,
        "isNovel": true,
        "isPromo": false
    },
    {
        "id": 182,
        "title": "Дрель-шуруповерт аккумуляторная ДА-13/18 М2 (Т), 18 В, 1,5 Ач NiCd Интерскол",
        "code": "00000146024",
        "price": 10360,
        "diameterChuck": 80,
        "producer": "Engy",
        "appointment": "Отвертка",
        "image": "//tdp.ru/images/p/ddd/a58dc-2633-11e5-b9a9-00259036a192_230x0_1.jpg",
        "hasBattery": true,
        "isNovel": false,
        "isPromo": false
    },
    {
        "id": 183,
        "title": "Дрель-шуруповерт аккумуляторная ДА-14,4 ЭР   14,4 В, 1,5 Ач NiCd Интерскол",
        "code": "00000102405",
        "price": 10567,
        "diameterChuck": 60,
        "producer": "Engy",
        "appointment": "Шуруповерт",
        "image": "//tdp.ru/images/p/267/c74aa-cca7-11e1-bbf2-00259036a114_230x0_1.jpg",
        "hasBattery": false,
        "isNovel": true,
        "isPromo": false
    },
    {
        "id": 184,
        "title": "Дрель-шуруповерт аккумуляторная ДА-18 ЭР,  18 В, 1,5 Ач NiCd Интерскол",
        "code": "00000102406",
        "price": 8200,
        "diameterChuck": 30,
        "producer": "Интерскол",
        "appointment": "Отвертка",
        "image": "//tdp.ru/images/p/cfa/2d09b-8823-11df-9b7f-001f29c68b0a_230x0_1.jpg",
        "hasBattery": false,
        "isNovel": true,
        "isPromo": true
    },
    {
        "id": 185,
        "title": "Дрель-шуруповерт аккумуляторная ДА-512/2, 12 В, 1,2 Ач NiCd Калибр",
        "code": "00000143896",
        "price": 8086,
        "diameterChuck": 30,
        "producer": "Engy",
        "appointment": "Дрель-шуруповерт",
        "image": "//tdp.ru/images/p/c2f/f8a18-f541-11e4-afe5-00259036a192_230x0_1.jpg",
        "hasBattery": true,
        "isNovel": false,
        "isPromo": true
    },
    {
        "id": 186,
        "title": "Дрель-шуруповерт аккумуляторная ДА-514,4/2, 14,4 В, 1,2 Ач NiCd Калибр",
        "code": "00000143897",
        "price": 3605,
        "diameterChuck": 10,
        "producer": "Engy",
        "appointment": "Дрель-шуруповерт",
        "image": "//tdp.ru/images/p/c9a/ca828-f541-11e4-afe5-00259036a192_230x0_1.jpg",
        "hasBattery": false,
        "isNovel": false,
        "isPromo": false
    },
    {
        "id": 187,
        "title": "Дрель-шуруповерт аккумуляторная ДА-518/2+, 18 В, 1,2 Ач NiCd, Калибр",
        "code": "00000153655",
        "price": 10096,
        "diameterChuck": 100,
        "producer": "Fixtec",
        "appointment": "Отвертка",
        "image": "//tdp.ru/images/p/cf3/44bce-aede-11e5-bed3-00259036a192_230x0_1.jpg",
        "hasBattery": false,
        "isNovel": true,
        "isPromo": true
    },
    {
        "id": 188,
        "title": "Дрель-шуруповерт аккумуляторная ДШ-3014К, 14,4 В, 1,3 Ач NiCd Энергомаш",
        "code": "00000102407",
        "price": 7700,
        "diameterChuck": 80,
        "producer": "Bosch",
        "appointment": "Дрель-шуруповерт",
        "image": "//tdp.ru/images/p/c6a/d0018-d587-11e1-bbf2-00259036a114_230x0_1.jpg",
        "hasBattery": true,
        "isNovel": true,
        "isPromo": false
    },
    {
        "id": 189,
        "title": "Дрель-шуруповерт сетевой DRL400A, 280Вт, Hammer ",
        "code": "00000139826",
        "price": 7905,
        "diameterChuck": 20,
        "producer": "Интерскол",
        "appointment": "Дрель-шуруповерт",
        "image": "//tdp.ru/images/p/ce8/cf84d-c0a5-11e4-afe5-00259036a192_230x0_1.jpg",
        "hasBattery": true,
        "isNovel": true,
        "isPromo": false
    },
    {
        "id": 190,
        "title": "Дрель-шуруповерт сетевой EED-280, 280 Вт, Engy",
        "code": "00000144712",
        "price": 3744,
        "diameterChuck": 90,
        "producer": "Fixtec",
        "appointment": "Шуруповерт",
        "image": "//tdp.ru/images/p/d65/edb6d-f3b1-11e4-afe5-00259036a192_230x0_1.jpg",
        "hasBattery": false,
        "isNovel": false,
        "isPromo": false
    },
    {
        "id": 191,
        "title": "Дрель-шуруповерт сетевой ДУ-21300, 300 Вт Энергомаш ",
        "code": "00000102408",
        "price": 11157,
        "diameterChuck": 40,
        "producer": "Engy",
        "appointment": "Дрель-шуруповерт",
        "image": "//tdp.ru/images/p/c6a/d0017-d587-11e1-bbf2-00259036a114_230x0_1.jpg",
        "hasBattery": false,
        "isNovel": true,
        "isPromo": false
    },
    {
        "id": 192,
        "title": "Дрель-шуруповерт сетевой ДШ-10/260Э2(Т), 260 Вт, Интерскол ",
        "code": "00000134902",
        "price": 9286,
        "diameterChuck": 90,
        "producer": "Интерскол",
        "appointment": "Дрель-шуруповерт",
        "image": "//tdp.ru/images/p/fbb/9b087-cad3-11e3-aced-00259036a114_230x0_1.jpg",
        "hasBattery": true,
        "isNovel": true,
        "isPromo": true
    },
    {
        "id": 193,
        "title": "Дрель-шуруповерт сетевой ДЭ-310ш, 310Вт, Калибр",
        "code": "00000153658",
        "price": 9175,
        "diameterChuck": 20,
        "producer": "Makita",
        "appointment": "Отвертка",
        "image": "//tdp.ru/images/p/8e1/6ef2e-aedf-11e5-bed3-00259036a192_230x0_1.jpg",
        "hasBattery": false,
        "isNovel": true,
        "isPromo": false
    },
    {
        "id": 194,
        "title": "Отвертка 6 насадок Эконом",
        "code": "00000105372",
        "price": 10637,
        "diameterChuck": 90,
        "producer": "Bosch",
        "appointment": "Шуруповерт",
        "image": "//tdp.ru/images/p/09d/da282-6842-11e1-865f-00259036a114_230x0_1.jpg",
        "hasBattery": false,
        "isNovel": false,
        "isPromo": true
    },
    {
        "id": 195,
        "title": "Отвертка аккумуляторная GSR MX2Drive 3,6 В, 1,5 Ач Li-Ion Bosch",
        "code": "00000136368",
        "price": 13606,
        "diameterChuck": 20,
        "producer": "Bosch",
        "appointment": "Дрель-шуруповерт",
        "image": "//tdp.ru/images/p/acc/7f4b7-08b8-11e4-94b6-002590c8c920_230x0_1.jpg",
        "hasBattery": false,
        "isNovel": false,
        "isPromo": false
    },
    {
        "id": 196,
        "title": "Отвертка индикаторная пластиковая ручка 140 мм Witte Профи ",
        "code": "00000126605",
        "price": 14075,
        "diameterChuck": 40,
        "producer": "Bosch",
        "appointment": "Дрель-шуруповерт",
        "image": "//tdp.ru/images/p/fc8/0839d-42c4-11e2-8d10-00259036a114_230x0_1.jpg",
        "hasBattery": true,
        "isNovel": true,
        "isPromo": false
    },
    {
        "id": 197,
        "title": "Отвертка крестовая PH0 60 мм Hesler Эконом",
        "code": "00000147624",
        "price": 2748,
        "diameterChuck": 100,
        "producer": "Makita",
        "appointment": "Шуруповерт",
        "image": "//tdp.ru/images/p/f2f/a30a0-7cbf-11e5-9d89-00259036a192_230x0_1.jpg",
        "hasBattery": false,
        "isNovel": false,
        "isPromo": true
    },
    {
        "id": 198,
        "title": "Отвертка крестовая PH0 60 мм Witte Профи",
        "code": "00000128665",
        "price": 10554,
        "diameterChuck": 80,
        "producer": "Fixtec",
        "appointment": "Отвертка",
        "image": "//tdp.ru/images/p/df6/25165-8fdf-11e2-b6f9-00259036a114_230x0_1.jpg",
        "hasBattery": false,
        "isNovel": true,
        "isPromo": true
    },
    {
        "id": 199,
        "title": "Отвертка крестовая PH1 80 мм  Hesler Эконом",
        "code": "00000147625",
        "price": 8058,
        "diameterChuck": 60,
        "producer": "Makita",
        "appointment": "Шуруповерт",
        "image": "//tdp.ru/images/p/5c8/f5c00-7c81-11e5-9d89-00259036a192_230x0_1.jpg",
        "hasBattery": true,
        "isNovel": true,
        "isPromo": true
    },
    {
        "id": 200,
        "title": "Отвертка крестовая PH1 80 мм \"MAXXPROplus\" Witte Профи",
        "code": "00000148973",
        "price": 11701,
        "diameterChuck": 70,
        "producer": "Fixtec",
        "appointment": "Шуруповерт",
        "image": "//tdp.ru/images/p/43c/5a489-dc71-11e5-bed3-00259036a192_230x0_1.jpg",
        "hasBattery": true,
        "isNovel": false,
        "isPromo": false
    },
    {
        "id": 201,
        "title": "Отвертка крестовая PH1 80 мм Witte Профи",
        "code": "00000128666",
        "price": 2908,
        "diameterChuck": 20,
        "producer": "Makita",
        "appointment": "Отвертка",
        "image": "//tdp.ru/images/p/df6/25166-8fdf-11e2-b6f9-00259036a114_230x0_1.jpg",
        "hasBattery": false,
        "isNovel": false,
        "isPromo": true
    },
    {
        "id": 202,
        "title": "Отвертка крестовая PH1 80 мм диэлектрическая 1000V Witte Профи",
        "code": "00000126608",
        "price": 10088,
        "diameterChuck": 70,
        "producer": "Интерскол",
        "appointment": "Дрель-шуруповерт",
        "image": "//tdp.ru/images/p/fc8/083a0-42c4-11e2-8d10-00259036a114_230x0_1.jpg",
        "hasBattery": false,
        "isNovel": true,
        "isPromo": false
    },
    {
        "id": 203,
        "title": "Отвертка крестовая PH2 100 мм  Hesler Эконом",
        "code": "00000147626",
        "price": 2684,
        "diameterChuck": 30,
        "producer": "Интерскол",
        "appointment": "Отвертка",
        "image": "//tdp.ru/images/p/7e2/ea9a0-7c87-11e5-9d89-00259036a192_230x0_1.jpg",
        "hasBattery": true,
        "isNovel": true,
        "isPromo": true
    },
    {
        "id": 204,
        "title": "Отвертка крестовая PH2 100 мм \"MAXXPROplus\" Witte Профи",
        "code": "00000148975",
        "price": 13770,
        "diameterChuck": 20,
        "producer": "Makita",
        "appointment": "Отвертка",
        "image": "//tdp.ru/images/p/4d5/96cbc-dc71-11e5-bed3-00259036a192_230x0_1.jpg",
        "hasBattery": true,
        "isNovel": false,
        "isPromo": true
    },
    {
        "id": 205,
        "title": "Отвертка крестовая PH2 100 мм Witte Профи",
        "code": "00000128667",
        "price": 10152,
        "diameterChuck": 50,
        "producer": "Fixtec",
        "appointment": "Шуруповерт",
        "image": "//tdp.ru/images/p/df6/25167-8fdf-11e2-b6f9-00259036a114_230x0_1.jpg",
        "hasBattery": true,
        "isNovel": false,
        "isPromo": true
    },
    {
        "id": 206,
        "title": "Отвертка крестовая PH2 100 мм диэлектрическая 1000V Witte Профи",
        "code": "00000126609",
        "price": 2994,
        "diameterChuck": 20,
        "producer": "Интерскол",
        "appointment": "Дрель-шуруповерт",
        "image": "//tdp.ru/images/p/fc8/083a1-42c4-11e2-8d10-00259036a114_230x0_1.jpg",
        "hasBattery": true,
        "isNovel": true,
        "isPromo": false
    },
    {
        "id": 207,
        "title": "Отвертка крестовая PH2 100 мм Эконом",
        "code": "00000105376",
        "price": 13996,
        "diameterChuck": 40,
        "producer": "Skil",
        "appointment": "Отвертка",
        "image": "//tdp.ru/images/p/908/25369-ba37-11df-9b7f-001f29c68b0a_230x0_1.jpg",
        "hasBattery": false,
        "isNovel": true,
        "isPromo": false
    },
    {
        "id": 208,
        "title": "Отвертка крестовая PH2 38 мм  Hesler Эконом",
        "code": "00000147627",
        "price": 4057,
        "diameterChuck": 80,
        "producer": "Skil",
        "appointment": "Шуруповерт",
        "image": "//tdp.ru/images/p/7ed/56840-7c81-11e5-9d89-00259036a192_230x0_1.jpg",
        "hasBattery": true,
        "isNovel": true,
        "isPromo": false
    },
    {
        "id": 209,
        "title": "Отвертка крестовая PH2 38 мм Эконом",
        "code": "00000133376",
        "price": 9877,
        "diameterChuck": 80,
        "producer": "Makita",
        "appointment": "Дрель-шуруповерт",
        "image": "//tdp.ru/images/p/604/d7fc4-8fb2-11e3-b1e6-00259036a114_230x0_1.jpg",
        "hasBattery": true,
        "isNovel": false,
        "isPromo": true
    },
    {
        "id": 210,
        "title": "Отвертка крестовая PH3 150 мм  Hesler Эконом",
        "code": "00000147628",
        "price": 10190,
        "diameterChuck": 100,
        "producer": "Engy",
        "appointment": "Отвертка",
        "image": "//tdp.ru/images/p/d80/57e80-7cbf-11e5-9d89-00259036a192_230x0_1.jpg",
        "hasBattery": true,
        "isNovel": true,
        "isPromo": false
    },
    {
        "id": 211,
        "title": "Отвертка крестовая PH3 150 мм Witte Профи",
        "code": "00000128668",
        "price": 14570,
        "diameterChuck": 70,
        "producer": "Engy",
        "appointment": "Шуруповерт",
        "image": "//tdp.ru/images/p/df6/25168-8fdf-11e2-b6f9-00259036a114_230x0_1.jpg",
        "hasBattery": true,
        "isNovel": false,
        "isPromo": false
    },
    {
        "id": 212,
        "title": "Отвертка крестовая PH3 150 мм Эконом",
        "code": "00000133377",
        "price": 8046,
        "diameterChuck": 10,
        "producer": "Skil",
        "appointment": "Отвертка",
        "image": "//tdp.ru/images/p/604/d7fc5-8fb2-11e3-b1e6-00259036a114_230x0_1.jpg",
        "hasBattery": true,
        "isNovel": false,
        "isPromo": true
    },
    {
        "id": 213,
        "title": "Отвертка крестовая PZ1  80 мм \"MAXXPROplus\" Witte Профи",
        "code": "00000148976",
        "price": 8546,
        "diameterChuck": 60,
        "producer": "Makita",
        "appointment": "Отвертка",
        "image": "//tdp.ru/images/p/4d5/96cca-dc71-11e5-bed3-00259036a192_230x0_1.jpg",
        "hasBattery": false,
        "isNovel": false,
        "isPromo": true
    },
    {
        "id": 214,
        "title": "Отвертка крестовая PZ1 75 мм  Hesler Эконом",
        "code": "00000147630",
        "price": 7371,
        "diameterChuck": 50,
        "producer": "Makita",
        "appointment": "Отвертка",
        "image": "//tdp.ru/images/p/a25/cce21-7c81-11e5-9d89-00259036a192_230x0_1.jpg",
        "hasBattery": false,
        "isNovel": false,
        "isPromo": false
    },
    {
        "id": 215,
        "title": "Отвертка крестовая PZ1 75 мм Эконом",
        "code": "00000105377",
        "price": 11765,
        "diameterChuck": 40,
        "producer": "Fixtec",
        "appointment": "Дрель-шуруповерт",
        "image": "//tdp.ru/images/p/853/948a8-b438-11df-9b7f-001f29c68b0a_230x0_1.jpg",
        "hasBattery": true,
        "isNovel": true,
        "isPromo": false
    },
    {
        "id": 216,
        "title": "Отвертка крестовая PZ1 80 мм Witte Профи",
        "code": "00000128669",
        "price": 8040,
        "diameterChuck": 50,
        "producer": "Bosch",
        "appointment": "Шуруповерт",
        "image": "//tdp.ru/images/p/df6/25169-8fdf-11e2-b6f9-00259036a114_230x0_1.jpg",
        "hasBattery": false,
        "isNovel": false,
        "isPromo": false
    },
    {
        "id": 217,
        "title": "Отвертка крестовая PZ2 100 мм  Hesler Эконом",
        "code": "00000147631",
        "price": 12468,
        "diameterChuck": 60,
        "producer": "Skil",
        "appointment": "Шуруповерт",
        "image": "//tdp.ru/images/p/b5e/ab9c0-7c81-11e5-9d89-00259036a192_230x0_1.jpg",
        "hasBattery": false,
        "isNovel": true,
        "isPromo": false
    },
    {
        "id": 218,
        "title": "Отвертка крестовая PZ2 100 мм Witte Профи",
        "code": "00000128530",
        "price": 12828,
        "diameterChuck": 30,
        "producer": "Makita",
        "appointment": "Отвертка",
        "image": "//tdp.ru/images/p/df6/2516a-8fdf-11e2-b6f9-00259036a114_230x0_1.jpg",
        "hasBattery": true,
        "isNovel": true,
        "isPromo": false
    },
    {
        "id": 219,
        "title": "Отвертка крестовая PZ2 100 мм Эконом",
        "code": "00000105378",
        "price": 10523,
        "diameterChuck": 30,
        "producer": "Makita",
        "appointment": "Отвертка",
        "image": "//tdp.ru/images/p/908/25371-ba37-11df-9b7f-001f29c68b0a_230x0_1.jpg",
        "hasBattery": true,
        "isNovel": false,
        "isPromo": true
    },
    {
        "id": 220,
        "title": "Отвертка крестовая PZ2  100 мм \"MAXXPROplus\" Witte Профи",
        "code": "00000148978",
        "price": 14648,
        "diameterChuck": 10,
        "producer": "Интерскол",
        "appointment": "Дрель-шуруповерт",
        "image": "//tdp.ru/images/p/540/8e968-dc71-11e5-bed3-00259036a192_230x0_1.jpg",
        "hasBattery": true,
        "isNovel": true,
        "isPromo": true
    },
    {
        "id": 221,
        "title": "Отвертка плоская 2,5х75 мм  Hesler Эконом",
        "code": "00000147632",
        "price": 12169,
        "diameterChuck": 60,
        "producer": "Fixtec",
        "appointment": "Дрель-шуруповерт",
        "image": "//tdp.ru/images/p/b6b/751a0-7c87-11e5-9d89-00259036a192_230x0_1.jpg",
        "hasBattery": true,
        "isNovel": true,
        "isPromo": true
    },
    {
        "id": 222,
        "title": "Отвертка плоская 2,5х75 мм диэлектрическая 1000V Witte Профи",
        "code": "00000126606",
        "price": 6399,
        "diameterChuck": 50,
        "producer": "Fixtec",
        "appointment": "Дрель-шуруповерт",
        "image": "//tdp.ru/images/p/fc8/0839e-42c4-11e2-8d10-00259036a114_230x0_1.jpg",
        "hasBattery": false,
        "isNovel": true,
        "isPromo": true
    },
    {
        "id": 223,
        "title": "Отвертка плоская 3,5х75 мм Witte Профи",
        "code": "00000128670",
        "price": 11795,
        "diameterChuck": 30,
        "producer": "Skil",
        "appointment": "Шуруповерт",
        "image": "//tdp.ru/images/p/df6/25161-8fdf-11e2-b6f9-00259036a114_230x0_1.jpg",
        "hasBattery": false,
        "isNovel": false,
        "isPromo": false
    },
    {
        "id": 224,
        "title": "Отвертка плоская 3,5х75 мм\"MAXXPROplus\" Witte Профи",
        "code": "00000148967",
        "price": 9788,
        "diameterChuck": 30,
        "producer": "Skil",
        "appointment": "Отвертка",
        "image": "//tdp.ru/images/p/620/03a9c-dc71-11e5-bed3-00259036a192_230x0_1.jpg",
        "hasBattery": false,
        "isNovel": false,
        "isPromo": true
    },
    {
        "id": 225,
        "title": "Отвертка плоская 3x75 мм ",
        "code": "00000105387",
        "price": 8638,
        "diameterChuck": 50,
        "producer": "Bosch",
        "appointment": "Дрель-шуруповерт",
        "image": "//tdp.ru/images/p/908/25372-ba37-11df-9b7f-001f29c68b0a_230x0_1.jpg",
        "hasBattery": false,
        "isNovel": true,
        "isPromo": false
    },
    {
        "id": 226,
        "title": "Отвертка плоская 3x75 мм  Hesler Эконом",
        "code": "00000147633",
        "price": 3872,
        "diameterChuck": 80,
        "producer": "Engy",
        "appointment": "Дрель-шуруповерт",
        "image": "//tdp.ru/images/p/6dd/3b560-7c81-11e5-9d89-00259036a192_230x0_1.jpg",
        "hasBattery": true,
        "isNovel": false,
        "isPromo": false
    },
    {
        "id": 227,
        "title": "Отвертка плоская 3х75 мм \"MAXXPROplus\" Witte Профи",
        "code": "00000148971",
        "price": 6260,
        "diameterChuck": 70,
        "producer": "Skil",
        "appointment": "Шуруповерт",
        "image": "//tdp.ru/images/p/620/03aa7-dc71-11e5-bed3-00259036a192_230x0_1.jpg",
        "hasBattery": true,
        "isNovel": true,
        "isPromo": true
    },
    {
        "id": 228,
        "title": "Отвертка плоская 3х75 мм Witte Профи",
        "code": "00000128671",
        "price": 4885,
        "diameterChuck": 20,
        "producer": "Engy",
        "appointment": "Дрель-шуруповерт",
        "image": "//tdp.ru/images/p/df6/25160-8fdf-11e2-b6f9-00259036a114_230x0_1.jpg",
        "hasBattery": false,
        "isNovel": true,
        "isPromo": false
    },
    {
        "id": 229,
        "title": "Отвертка плоская 4x75 мм  Hesler Эконом",
        "code": "00000147634",
        "price": 12358,
        "diameterChuck": 30,
        "producer": "Интерскол",
        "appointment": "Шуруповерт",
        "image": "//tdp.ru/images/p/440/10ec0-7c88-11e5-9d89-00259036a192_230x0_1.jpg",
        "hasBattery": false,
        "isNovel": false,
        "isPromo": false
    },
    {
        "id": 230,
        "title": "Отвертка плоская 4x75 мм Эконом",
        "code": "00000133373",
        "price": 13636,
        "diameterChuck": 70,
        "producer": "Skil",
        "appointment": "Дрель-шуруповерт",
        "image": "//tdp.ru/images/p/604/d7fc2-8fb2-11e3-b1e6-00259036a114_230x0_1.jpg",
        "hasBattery": false,
        "isNovel": true,
        "isPromo": false
    },
    {
        "id": 231,
        "title": "Отвертка плоская 4х100 мм  Hesler Эконом",
        "code": "00000147635",
        "price": 8746,
        "diameterChuck": 20,
        "producer": "Интерскол",
        "appointment": "Отвертка",
        "image": "//tdp.ru/images/p/ddc/96140-7c80-11e5-9d89-00259036a192_230x0_1.jpg",
        "hasBattery": false,
        "isNovel": false,
        "isPromo": false
    },
    {
        "id": 232,
        "title": "Отвертка плоская 4х100 мм \"MAXXPROplus\" Witte Профи",
        "code": "00000148969",
        "price": 4530,
        "diameterChuck": 70,
        "producer": "Engy",
        "appointment": "Шуруповерт",
        "image": "//tdp.ru/images/p/687/434e8-dc71-11e5-bed3-00259036a192_230x0_1.jpg",
        "hasBattery": false,
        "isNovel": false,
        "isPromo": false
    },
    {
        "id": 233,
        "title": "Отвертка плоская 4х100 мм Witte Профи",
        "code": "00000128672",
        "price": 8649,
        "diameterChuck": 70,
        "producer": "Fixtec",
        "appointment": "Отвертка",
        "image": "//tdp.ru/images/p/df6/25162-8fdf-11e2-b6f9-00259036a114_230x0_1.jpg",
        "hasBattery": false,
        "isNovel": true,
        "isPromo": true
    },
    {
        "id": 234,
        "title": "Отвертка плоская 5,5х125 мм Witte Профи",
        "code": "00000128673",
        "price": 2590,
        "diameterChuck": 70,
        "producer": "Fixtec",
        "appointment": "Дрель-шуруповерт",
        "image": "//tdp.ru/images/p/df6/25163-8fdf-11e2-b6f9-00259036a114_230x0_1.jpg",
        "hasBattery": true,
        "isNovel": false,
        "isPromo": false
    },
    {
        "id": 235,
        "title": "Отвертка плоская 5,5х125 мм диэлектрическая 1000V Witte Профи",
        "code": "00000126607",
        "price": 10721,
        "diameterChuck": 50,
        "producer": "Fixtec",
        "appointment": "Шуруповерт",
        "image": "//tdp.ru/images/p/fc8/0839f-42c4-11e2-8d10-00259036a114_230x0_1.jpg",
        "hasBattery": false,
        "isNovel": false,
        "isPromo": true
    },
    {
        "id": 236,
        "title": "Отвертка плоская 5х100 мм  Hesler Эконом",
        "code": "00000147636",
        "price": 8078,
        "diameterChuck": 60,
        "producer": "Fixtec",
        "appointment": "Отвертка",
        "image": "//tdp.ru/images/p/e5d/6b9c0-7cbf-11e5-9d89-00259036a192_230x0_1.jpg",
        "hasBattery": false,
        "isNovel": false,
        "isPromo": false
    },
    {
        "id": 237,
        "title": "Отвертка плоская 5х100 мм Эконом",
        "code": "00000105392",
        "price": 3156,
        "diameterChuck": 30,
        "producer": "Skil",
        "appointment": "Шуруповерт",
        "image": "//tdp.ru/images/p/853/948aa-b438-11df-9b7f-001f29c68b0a_230x0_1.jpg",
        "hasBattery": true,
        "isNovel": false,
        "isPromo": false
    },
    {
        "id": 238,
        "title": "Отвертка плоская 6,5х125 мм Witte Профи",
        "code": "00000128531",
        "price": 7597,
        "diameterChuck": 70,
        "producer": "Skil",
        "appointment": "Дрель-шуруповерт",
        "image": "//tdp.ru/images/p/df6/25164-8fdf-11e2-b6f9-00259036a114_230x0_1.jpg",
        "hasBattery": true,
        "isNovel": false,
        "isPromo": false
    },
    {
        "id": 239,
        "title": "Отвертка плоская 6x100 мм  Hesler Эконом",
        "code": "00000147637",
        "price": 10815,
        "diameterChuck": 10,
        "producer": "Интерскол",
        "appointment": "Отвертка",
        "image": "//tdp.ru/images/p/f6f/2aa00-7c80-11e5-9d89-00259036a192_230x0_1.jpg",
        "hasBattery": true,
        "isNovel": false,
        "isPromo": true
    },
    {
        "id": 240,
        "title": "Отвертка плоская 6x100 мм Эконом",
        "code": "00000133374",
        "price": 9998,
        "diameterChuck": 60,
        "producer": "Skil",
        "appointment": "Отвертка",
        "image": "//tdp.ru/images/p/62e/8e447-99e3-11e3-ae3d-00259036a114_230x0_1.jpg",
        "hasBattery": true,
        "isNovel": true,
        "isPromo": false
    },
    {
        "id": 241,
        "title": "Отвертка плоская 6x38 мм  Hesler Эконом",
        "code": "00000147638",
        "price": 4293,
        "diameterChuck": 10,
        "producer": "Интерскол",
        "appointment": "Шуруповерт",
        "image": "//tdp.ru/images/p/0b4/16500-7c81-11e5-9d89-00259036a192_230x0_1.jpg",
        "hasBattery": true,
        "isNovel": false,
        "isPromo": true
    },
    {
        "id": 242,
        "title": "Отвертка плоская 6x38 мм Эконом",
        "code": "00000133372",
        "price": 10317,
        "diameterChuck": 70,
        "producer": "Bosch",
        "appointment": "Отвертка",
        "image": "//tdp.ru/images/p/559/03d03-9964-11e3-ae3d-00259036a114_230x0_1.jpg",
        "hasBattery": false,
        "isNovel": false,
        "isPromo": true
    },
    {
        "id": 243,
        "title": "Отвертка плоская 8x150 мм  Hesler Эконом",
        "code": "00000147639",
        "price": 3250,
        "diameterChuck": 40,
        "producer": "Bosch",
        "appointment": "Шуруповерт",
        "image": "//tdp.ru/images/p/701/40440-7c88-11e5-9d89-00259036a192_230x0_1.jpg",
        "hasBattery": false,
        "isNovel": false,
        "isPromo": false
    },
    {
        "id": 244,
        "title": "Отвертка плоская 8x150 мм Эконом",
        "code": "00000133375",
        "price": 15847,
        "diameterChuck": 50,
        "producer": "Fixtec",
        "appointment": "Дрель-шуруповерт",
        "image": "//tdp.ru/images/p/604/d7fc3-8fb2-11e3-b1e6-00259036a114_230x0_1.jpg",
        "hasBattery": false,
        "isNovel": false,
        "isPromo": false
    },
    {
        "id": 245,
        "title": "Отвертка под биту \"MAXXPROplus\" Witte Профи",
        "code": "00000148979",
        "price": 15035,
        "diameterChuck": 40,
        "producer": "Engy",
        "appointment": "Отвертка",
        "image": "//tdp.ru/images/p/6ed/78585-dc71-11e5-bed3-00259036a192_230x0_1.jpg",
        "hasBattery": false,
        "isNovel": true,
        "isPromo": false
    },
    {
        "id": 246,
        "title": "Отвертка под биту Witte Профи",
        "code": "00000128674",
        "price": 12058,
        "diameterChuck": 80,
        "producer": "Engy",
        "appointment": "Дрель-шуруповерт",
        "image": "//tdp.ru/images/p/df6/2516b-8fdf-11e2-b6f9-00259036a114_230x0_1.jpg",
        "hasBattery": false,
        "isNovel": true,
        "isPromo": false
    },
    {
        "id": 247,
        "title": "Отвертка реверсивная 12 насадок Jettools Профи",
        "code": "00000133926",
        "price": 9104,
        "diameterChuck": 100,
        "producer": "Fixtec",
        "appointment": "Отвертка",
        "image": "//tdp.ru/images/p/9a3/92cb1-a9bc-11e3-b8d5-00259036a114_230x0_1.jpg",
        "hasBattery": false,
        "isNovel": true,
        "isPromo": false
    },
    {
        "id": 248,
        "title": "Отвертка реверсивная Т-образная под биту Jettools Профи",
        "code": "00000133927",
        "price": 7811,
        "diameterChuck": 60,
        "producer": "Skil",
        "appointment": "Шуруповерт",
        "image": "//tdp.ru/images/p/a97/1ddf7-a9bc-11e3-b8d5-00259036a114_230x0_1.jpg",
        "hasBattery": true,
        "isNovel": false,
        "isPromo": true
    },
    {
        "id": 249,
        "title": "Отвертка крестовая PH-1x75 мм, ударная Кобальт Стандарт",
        "code": "00000155530",
        "price": 7076,
        "diameterChuck": 30,
        "producer": "Skil",
        "appointment": "Шуруповерт",
        "image": "//tdp.ru/images/p/fbe/cb83e-0708-11e6-bed3-00259036a192_230x0_1.jpg",
        "hasBattery": false,
        "isNovel": false,
        "isPromo": false
    },
    {
        "id": 250,
        "title": "Отвертка крестовая PH-2x100 мм, ударная Кобальт Стандарт",
        "code": "00000155531",
        "price": 7194,
        "diameterChuck": 10,
        "producer": "Интерскол",
        "appointment": "Шуруповерт",
        "image": "//tdp.ru/images/p/079/34e37-0709-11e6-bed3-00259036a192_230x0_1.jpg",
        "hasBattery": false,
        "isNovel": false,
        "isPromo": false
    },
    {
        "id": 251,
        "title": "Отвертка крестовая PH-2x150 мм, ударная Кобальт Стандарт",
        "code": "00000155532",
        "price": 14412,
        "diameterChuck": 80,
        "producer": "Fixtec",
        "appointment": "Шуруповерт",
        "image": "//tdp.ru/images/p/90b/28ae0-0706-11e6-bed3-00259036a192_230x0_1.jpg",
        "hasBattery": false,
        "isNovel": false,
        "isPromo": true
    },
    {
        "id": 252,
        "title": "Отвертка крестовая PH-3x150 мм, ударная Кобальт Стандарт",
        "code": "00000155533",
        "price": 2758,
        "diameterChuck": 50,
        "producer": "Интерскол",
        "appointment": "Дрель-шуруповерт",
        "image": "//tdp.ru/images/p/9c0/a939c-0706-11e6-bed3-00259036a192_230x0_1.jpg",
        "hasBattery": true,
        "isNovel": false,
        "isPromo": false
    },
    {
        "id": 253,
        "title": "Отвертка плоская 5,5x75 мм, ударная  Кобальт Стандарт",
        "code": "00000155522",
        "price": 14931,
        "diameterChuck": 40,
        "producer": "Интерскол",
        "appointment": "Дрель-шуруповерт",
        "image": "//tdp.ru/images/p/dce/a51bb-0706-11e6-bed3-00259036a192_230x0_1.jpg",
        "hasBattery": false,
        "isNovel": false,
        "isPromo": false
    },
    {
        "id": 254,
        "title": "Отвертка плоская 6,5x100 мм , ударная Кобальт Стандарт",
        "code": "00000155526",
        "price": 14511,
        "diameterChuck": 70,
        "producer": "Bosch",
        "appointment": "Отвертка",
        "image": "//tdp.ru/images/p/14a/3b49c-0709-11e6-bed3-00259036a192_230x0_1.jpg",
        "hasBattery": true,
        "isNovel": false,
        "isPromo": true
    },
    {
        "id": 255,
        "title": "Отвертка плоская 6,5x150 мм, ударная Кобальт Стандарт",
        "code": "00000155527",
        "price": 11830,
        "diameterChuck": 20,
        "producer": "Makita",
        "appointment": "Дрель-шуруповерт",
        "image": "//tdp.ru/images/p/1fd/ccb84-0709-11e6-bed3-00259036a192_230x0_1.jpg",
        "hasBattery": false,
        "isNovel": false,
        "isPromo": false
    },
    {
        "id": 256,
        "title": "Отвертка плоская 8 x150 мм , ударная Кобальт Стандарт",
        "code": "00000155528",
        "price": 3080,
        "diameterChuck": 40,
        "producer": "Makita",
        "appointment": "Шуруповерт",
        "image": "//tdp.ru/images/p/2a5/e98da-0709-11e6-bed3-00259036a192_230x0_1.jpg",
        "hasBattery": true,
        "isNovel": false,
        "isPromo": true
    },
    {
        "id": 257,
        "title": "Отвертка плоская 8 x200 мм, ударная Кобальт Стандарт",
        "code": "00000155529",
        "price": 10891,
        "diameterChuck": 60,
        "producer": "Fixtec",
        "appointment": "Отвертка",
        "image": "//tdp.ru/images/p/3b4/d399c-0709-11e6-bed3-00259036a192_230x0_1.jpg",
        "hasBattery": true,
        "isNovel": false,
        "isPromo": true
    },
    {
        "id": 258,
        "title": "Шуруповерт сетевой 6821, 570 Вт, Makita",
        "code": "00000109619",
        "price": 16094,
        "diameterChuck": 20,
        "producer": "Bosch",
        "appointment": "Дрель-шуруповерт",
        "image": "//tdp.ru/images/p/a05/89048-790b-11df-9b7f-001f29c68b0a_230x0_1.jpg",
        "hasBattery": true,
        "isNovel": false,
        "isPromo": false
    },
    {
        "id": 259,
        "title": "Шуруповерт сетевой FS4000, 570 Вт, Makita",
        "code": "00000147209",
        "price": 5204,
        "diameterChuck": 60,
        "producer": "Makita",
        "appointment": "Дрель-шуруповерт",
        "image": "//tdp.ru/images/p/805/d36a1-50a4-11e5-b9a9-00259036a192_230x0_1.jpg",
        "hasBattery": false,
        "isNovel": false,
        "isPromo": true
    },
    {
        "id": 260,
        "title": "Шуруповерт сетевой ударный TD 0101, 230 Вт Makita",
        "code": "00000129615",
        "price": 7980,
        "diameterChuck": 30,
        "producer": "Engy",
        "appointment": "Дрель-шуруповерт",
        "image": "//tdp.ru/images/p/b8c/3d876-bb85-11e2-99f1-00259036a114_230x0_1.jpg",
        "hasBattery": true,
        "isNovel": false,
        "isPromo": true
    },
    {
        "id": 261,
        "title": "Шуруповерт сетевой ударный TD0101F, 230 Вт Makita",
        "code": "00000147210",
        "price": 5608,
        "diameterChuck": 40,
        "producer": "Engy",
        "appointment": "Отвертка",
        "image": "//tdp.ru/images/p/b49/7961f-50a4-11e5-b9a9-00259036a192_230x0_1.jpg",
        "hasBattery": false,
        "isNovel": false,
        "isPromo": false
    },
    {
        "id": 262,
        "title": "Шуруповерт сетевой Ш-8/700 ЭР, 710 Вт Интерскол",
        "code": "00000129625",
        "price": 14555,
        "diameterChuck": 10,
        "producer": "Engy",
        "appointment": "Дрель-шуруповерт",
        "image": "//tdp.ru/images/p/c88/e5542-b880-11e2-99f1-00259036a114_230x0_1.jpg",
        "hasBattery": true,
        "isNovel": true,
        "isPromo": false
    }
]